Workbook
Name BOYS: #REF!
Name Canada: 'Dependent dropdown'!$E$4:$E$6
Name China: 'Dependent dropdown'!$D$4:$D$6
Name GIRLS: #REF!
Name India: 'Dependent dropdown'!$B$4:$B$8
Name Malaysia: 'Dependent dropdown'!$C$4:$C$6
Name Matrix_A: Matrices!$B$4:$D$5
Name Matrix_F: Matrices!$I$36:$K$37
Name Matrix_H: Matrices!$O$21:$O$23
Name Matrix_P: Matrices!$O$17:$Q$18
Name Matrix_Q: Matrices!$O$21:$Q$23
Name Matrix_S: Matrices!$M$36:$M$38
Name Matrix_X: Matrices!$B$18:$D$19
Name Matrix_Y: Matrices!$B$22:$D$23
Name Slicer_City: #N/A
Name Slicer_City1: #N/A
Name Slicer_City2: #N/A
Name Slicer_Customer_type: #N/A
Name Slicer_Customer_type1: #N/A
Name Slicer_Customer_type2: #N/A
Name Slicer_Date: #N/A
Name Slicer_Gender: #N/A
Name Slicer_Gender1: #N/A
Name Slicer_Rating: #N/A
Name Slicer_Rating1: #N/A
Name Slicer_Rating2: #N/A

Sheet Data Cleaning
B2: DATA CLEANING
B4: Dirty_Table | K4: Cleaned_Table
B5: Order ID | C5: Customer Name | D5: Email | E5: Order Date | F5: Product | G5: Quantity | H5: Price ($) | I5: Country | K5: Order ID | L5: Customer Name | M5: Email | N5: Order Date | O5: Product | P5: Quantity | Q5: Price ($) | R5: Country | T5: S.NO. | U5: Errors Found | V5: Steps that I did :
B6: 1001 | C6: John Smith | D6: johnsmith@gmail.com | E6: 2023-01-15 | F6: Shoes | G6: 2 | H6: 59.99 | I6: USA | K6: 1001 | L6: =TRIM(C6) -> John Smith | M6: johnsmith@gmail.com | N6: 44941 | O6: Shoes | P6: 2 | Q6: 59.99 | R6: USA | T6: 1 | U6: Order ID – Duplicate values (1002 repeated) | V6: Used Remove Duplicates and reassigned Order IDs sequentially
B7: 1002 | C7: Sara Connor | D7: saraconnor@gmail.com | E7: 01/18/2023 | F7: shooes | G7: 1 | H7: 49.99 | I7: usa | K7: 1002 | L7: =TRIM(C7) -> Sara Connor | M7: saraconnor@gmail.com | N7: 44944 | O7: Shoes | P7: 1 | Q7: 49.99 | R7: USA | T7: 2 | U7: Customer Name – Inconsistent casing | V7: Applied TRIM to remove unnecessary spaces
B8: 1003 | C8: Michael Brown | E8: 2023/01/20 | F8: Hat | G8: 3 | H8: 19.99 | I8: United States | K8: 1003 | L8: =TRIM(C8) -> Michael Brown | M8: - | N8: 44946 | O8: Hat | P8: 3 | Q8: 19.99 | R8: USA | T8: 3 | U8: Email – Missing values (blank cells) | V8: Replaced blanks with “-” (Find & Replace)
B9: 1002 | C9: Sara Connor | D9: saraconnor@gmail.com | E9: 2023-01-18 | F9: Shoes | G9: 1 | H9: 49.99 | I9: USA | K9: 1004 | L9: =TRIM(C9) -> Sara Connor | M9: saraconnor@gmail.com | N9: 44944 | O9: Shoes | P9: 1 | Q9: 49.99 | R9: USA | T9: 4 | U9: Email – Extra spaces in email | V9: Removed spaces using Find & Replace
B10: 1005 | C10: Anna Lee | D10: anna.lee @yahoo.com | E10: Jan 25, 23 | F10: Jacket | H10: 89.99 | I10: Canada | K10: 1005 | L10: =TRIM(C10) -> Anna Lee | M10: anna.lee@yahoo.com | N10: 44951 | O10: Jacket | P10: - | Q10: 89.99 | R10: Canada | T10: 5 | U10: Email – Invalid domain (.inc) | V10: Corrected/verified domain format (Find & Replace)
B11: 1006 | C11: Jon Smith | D11: johnsmith@gmail .com | E11: 2023-01-28 | F11: Socks | G11: 5 | H11: 5.5 | I11: U.S.A. | K11: 1006 | L11: =TRIM(C11) -> Jon Smith | M11: johnsmith@gmail.com | N11: 44954 | O11: Socks | P11: 5 | Q11: 5.5 | R11: USA | T11: 6 | U11: Order Date – Mixed formats | V11: Standardized using Text to Columns
B12: 1007 | C12: Robert Brown | D12: robertbrown@gmail.com | E12: 2023-02-02 | F12: Hat | G12: 2 | H12: 20 | I12: U.S | K12: 1007 | L12: =TRIM(C12) -> Robert Brown | M12: robertbrown@gmail.com | N12: 44959 | O12: Hat | P12: 2 | Q12: 20 | R12: USA | T12: 7 | U12: Product – Inconsistent naming | V12: Standardized using Find & Replace
B13: 1008 | C13: Sarah Connorr | D13: saraconnor@gmail.com | E13: 2023-02-05 | F13: Shoes | G13: two | H13: 59.99 | I13: USA | K13: 1008 | L13: =TRIM(C13) -> Sarah Connorr | M13: saraconnor@gmail.com | N13: 44962 | O13: Shoes | P13: 2 | Q13: 59.99 | R13: USA | T13: 8 | U13: Quantity – Text value (two) | V13: Converted to numeric (2)
B14: 1009 | C14: Anna Lee | D14: anna.lee@yahoo.com | E14: 2023-02-10 | F14: jacket | G14: 1 | H14: 89.99 | I14: CANADA | K14: 1009 | L14: =TRIM(C14) -> Anna Lee | M14: anna.lee@yahoo.com | N14: 44967 | O14: Jacket | P14: 1 | Q14: 89.99 | R14: Canada | T14: 9 | U14: Quantity – Stored as text | V14: Converted to proper number format
C15: Mike Wazowski | D15: mikew@monsters.inc | E15: 2023-02-12 | F15: Sneakers | G15: 1 | H15: 75 | I15: USA | K15: 1010 | L15: =TRIM(C15) -> Mike Wazowski | M15: mikew@monsters.com | N15: 44969 | O15: Sneakers | P15: 1 | Q15: 75 | R15: USA | T15: 10 | U15: Price – Inconsistent decimal values | V15: Converted to Number format and standardized decimals
T16: 11 | U16: Country – Inconsistent values | V16: Standardized naming using Find & Replace

Sheet Data Validation
B2: DATA VALIDATION | F2: Example | H2: QUESTIONS TO PRACTICE | I2: ANSWER COLUMN | K2: 1 | L2: 2 | M2: 3 | N2: 4 | O2: 5 | P2: 6
B3: S.no. | C3: Steps to Data Validation | D3: Example | F3: 18 | H3: 1. Value less than 30 | I3: K | K3: 15 | L3: -15 | M3: 1.5 | N3: 45292 | O3: 0.41678241 | P3: Shivam
B4: 1 | C4: Select a column like : F | D4: F | F4: 19 | H4: 2. Value equal to -15 | I4: L | K4: 16 | L4: -15 | M4: 2.5 | N4: 45415 | O4: 0.45844907 | P4: Shubh
B5: 2 | C5: Go to Data Tab | D5: ALT + A | F5: 67 | H5: 3. Decimal between 1.5 and 9.5 | I5: M | K5: 17 | L5: -15 | M5: 3.5 | N5: 45416 | O5: 0.50011574 | P5: Deva
B6: 3 | C6: Select Data Validation | D6: ALT + A + V + V | F6: 48 | H6: 4. Date between 1 Jan 2024 and 31 Dec 2024 | I6: N | K6: 18 | L6: -15 | M6: 4.5 | N6: 45417 | O6: 0.54178241 | P6: Adam Smith
B7: 4 | C7: Apply Settings : | D7: Allow: Whole Number | F7: 22 | H7: 5. Time between 9 AM and 6 PM | I7: O | K7: 19 | L7: -15 | M7: 5.5 | N7: 45418 | O7: 0.58344907 | P7: Rahul
D8: Condition: Greater than or equal to (>=) | F8: 56 | H8: 6. Text length should be maximum 10 characters | I8: P | K8: 20 | L8: -15 | M8: 6.5 | N8: 45419 | O8: 0.44444444 | P8: Priya
D9: Minimum Value: 18 | F9: 24 | K9: 21 | L9: -15 | M9: 7.5 | N9: 45451 | O9: 0.48611111 | P9: Aman
D10: Uncheck Ignore Blank if required | F10: 25 | K10: 22 | L10: -15 | M10: 8.5 | N10: 45483 | O10: 0.52777778 | P10: Neha
B11: 5 | C11: Set Input Message : | D11: Title: Instructions | F11: 26 | K11: 23 | L11: -15 | M11: 9.5 | N11: 45515 | O11: 0.56944444 | P11: Kunal
D12: Input Message: Enter a value greater than or equal to 18 only | F12: 99 | K12: 24 | L12: -15 | M12: 4 | N12: 45547 | O12: 0.61111111 | P12: Riya
B13: 6 | C13: Set Error Alert : | D13: Title: Error | F13: 21 | K13: 25 | L13: -15 | M13: 5.6 | N13: 45579 | O13: 0.65277778 | P13: Arjun
D14: Error Message: You have entered an invalid value | F14: 29 | K14: 26 | L14: -15 | M14: 6.6 | N14: 45611 | O14: 0.69444444 | P14: Sneha
K15: 27 | L15: -15 | M15: 7.6 | N15: 45643 | O15: 0.73611111 | P15: Varun
K16: 28 | L16: -15 | M16: 8.6 | N16: 45644 | O16: 0.75 | P16: Mohit
K17: 29 | L17: -15 | M17: 4.6 | N17: 45645 | O17: 0.74998843 | P17: Jeffery

Sheet Dependent dropdown
B2: Dependent Dropdown | G2: Example | J2: S.no. | K2: Steps | L2: Example
B3: India | C3: Malaysia | D3: China | E3: Canada | G3: COUNTRIES | H3: CITIES | J3: 1 | K3: Create Named Ranges using Create from Selection | L3: Select the complete data (including headings) | Q3: name select kr
B4: Mumbai | C4: Kuala Lumpur | D4: Bejing | E4: Toronto | G4: India | H4: Delhi | L4: Go to Formulas → Create from Selection | Q4: create from seelction
B5: Hyderabad | C5: Johor Bahru | D5: Guangzhou | E5: Ottawa | G5: Malaysia | H5: Johor Bahru | L5: Press Ctrl + Shift + F3 | Q5: ctrl + shift + f3
B6: Bangalore | C6: Kuching | D6: Shanghai | E6: Calgary | G6: China | H6: Guangzhou | L6: Tick Top Row and click OK
B7: Chennai | G7: Canada | H7: Ottawa
B8: Delhi | G8: India | H8: Hyderabad | J8: 2 | K8: Create First Dropdown (Countries – Column G) | L8: Select cell G4
L9: Go to Data → Data Validation → List
L10: In Source, enter: =$B$3:$E$3
J11: 3 | K11: Create Second Dropdown (Cities – Column H) | L11: Select cell H4
L12: Go to Data → Data Validation → List
L13: In Source, enter: =INDIRECT(G4)

Sheet Custom Data Validation
B2: Custom Data Validation (ISTEXT) | G2: Only non-numeric values are allowed | J2: Custom Data Validation (OR) | N2: Allow Specific Values (OR) | Q2: Custom Data Validation (AND) | U2: Allow Specific Values (AND)
B3: S.no. | C3: Steps for Custom Data Validation (Allow Only Text) | D3: Example | G3: A | J3: S.no. | K3: Steps for Custom Data Validation (Allow Only Text) | L3: Example | N3: SECURITY | Q3: S.no. | R3: Steps for Custom Data Validation (Allow Only Text) | S3: Example | U3: 11
B4: 1 | C4: Select the column | D4: Column G | G4: A123 | J4: 1 | K4: Select the column | L4: Column N | N4: ACCOUNTS | Q4: 1 | R4: Select the column | S4: Column N | U4: 56
B5: 2 | C5: Go to Data tab | D5: Alt + A | G5: 123A | J5: 2 | K5: Go to Data tab | L5: Alt + A | N5: IT | Q5: 2 | R5: Go to Data tab | S5: Alt + A | U5: 76
B6: 3 | C6: Click on Data Validation | D6: Alt + A + V + V | G6: ADAM@SMITH | J6: 3 | K6: Click on Data Validation | L6: Alt + A + V + V | N6: ACCOUNTS | Q6: 3 | R6: Click on Data Validation | S6: Alt + A + V + V | U6: 45
B7: 4 | C7: In Allow, select: Custom | G7: 3H# | J7: 4 | K7: In Allow, select: Custom | N7: IT | Q7: 4 | R7: In Allow, select: Custom | U7: 99
B8: 5 | C8: Enter the formula : =ISTEXT(G1) | D8: '=ISTEXT(G1)" | G8: Abh | J8: 5 | K8: Enter the formula : =OR(N1="ACCOUNTS",N1="IT",N1="SECURITY") | N8: SECURITY | Q8: 5 | R8: Enter the formula : =AND(A1>10, A1<100) | U8: 16
B9: 6 | C9: Click Ok | J9: 6 | K9: Click Ok | Q9: 6 | R9: Click Ok

Sheet Matrices
B2: MATRICES
B3: Matrix_A | F3: Ques: | G3: Ans : | K3: S.no. | L3: Define name of a matrix | N3: Ques: | O3: Ans : | V3: Ques:
B4: 55 | C4: 45 | D4: 60 | F4: Add 5 | G4: =B4+5 -> 60 | H4: =C4+5 -> 50 | I4: =D4+5 -> 65 | K4: 1 | L4: Select the whole Matrix rows and column | N4: Add 5 | O4: {=Matrix_A+5} -> 60 | P4: 50 | Q4: 65 | V4: A shop sells three types of fruits: apples, bananas, and oranges. The shopkeeper records the number of fruits sold over two days:
B5: 40 | C5: 20 | D5: 65 | G5: =B5+5 -> 45 | H5: =C5+5 -> 25 | I5: =D5+5 -> 70 | K5: 2 | L5: Go to Formulas tab | O5: 45 | P5: 25 | Q5: 70 | V5: On Monday, 50 apples, 30 bananas, and 20 oranges were sold.
K6: 3 | L6: Click on Define Name | V6: On Tuesday, 60 apples, 40 bananas, and 25 oranges were sold.
F7: Subtract 5 | G7: =B4-5 -> 50 | H7: =C4-5 -> 40 | I7: =D4-5 -> 55 | N7: Subtract 5 | O7: {=Matrix_A-5} -> 50 | P7: 40 | Q7: 55 | V7: Q: Represent this data in matrix form.
G8: =B5-5 -> 35 | H8: =C5-5 -> 15 | I8: =D5-5 -> 60 | K8: S.no. | L8: Array Formula | O8: 35 | P8: 15 | Q8: 60 | V8: The selling prices per fruit (in) are:
K9: 1 | L9: Select the output range | V9: Apple: 10 each | AD9: Apples | AE9: Bananas | AF9: Oranges | AH9: SP OF FRUITS
F10: * by 5 | G10: =B4*5 -> 275 | H10: =C4*5 -> 225 | I10: =D4*5 -> 300 | K10: 2 | L10: Type the formula (e.g. =Matrix_A+5) | N10: * by 5 | O10: {=Matrix_A*5} -> 275 | P10: 225 | Q10: 300 | V10: Banana: 5 each | AC10: MONDAY | AD10: 50 | AE10: 30 | AF10: 20 | AH10: 10
G11: =B5*5 -> 200 | H11: =C5*5 -> 100 | I11: =D5*5 -> 325 | K11: 3 | L11: Press Ctrl + Shift + Enter | O11: 200 | P11: 100 | Q11: 325 | V11: Orange: 8 each | AC11: TUESDAY | AD11: 60 | AE11: 40 | AF11: 25 | AH11: 5
V12: Find the revenue on mon and Tuesday | AH12: 8
F13: Divide by 5 | G13: =B4/5 -> 11 | H13: =C4/5 -> 9 | I13: =D4/5 -> 12 | N13: Divide by 5 | O13: {=Matrix_A/5} -> 11 | P13: 9 | Q13: 12
G14: =B5/5 -> 8 | H14: =C5/5 -> 4 | I14: =D5/5 -> 13 | O14: 8 | P14: 4 | Q14: 13 | AC14: Revenue | AD14: Monday | AE14: {=MMULT(AD10:AF11,AH10:AH12)} -> 810
AD15: Tuesday | AE15: 1000
B16: 2 MATRICES | K16: S.no. | L16: 2 Matrices Multiplication | O16: Matrix_G | S16: Ques: | T16: Ans :
B17: Matrix_X | F17: Ques: | G17: Ans : | K17: 1 | L17: Select output range (rows of P × columns of Q) | O17: 1 | P17: 2 | Q17: 3 | S17: G*H | T17: {=MMULT(O17:Q18,O21:O23)} -> 50
B18: 54 | C18: 74 | D18: 88 | F18: X+Y | G18: {=Matrix_X+Matrix_Y} -> 88 | H18: 103 | I18: 127 | K18: 2 | L18: Type formula =MMULT(P, Q) | O18: 4 | P18: 5 | Q18: 6 | T18: 122
B19: 58 | C19: 39 | D19: 21 | G19: 114 | H19: 93 | I19: 110 | K19: 3 | L19: Ctrl + Shift + Enter | V19: Ques:
O20: Matrix_H | V20: Three students appeared for four subjects: Math, Physics, Chemistry, and English. Their marks are:
B21: Matrix_Y | F21: X-Y | G21: {=Matrix_X-Matrix_Y} -> 20 | H21: 45 | I21: 49 | O21: 7 | V21: Student 1: 85, 78, 92, 88
B22: 34 | C22: 29 | D22: 39 | G22: 2 | H22: -15 | I22: -68 | O22: 8 | V22: Student 2: 90, 82, 89, 84
B23: 56 | C23: 54 | D23: 89 | O23: 9 | V23: Student 3: 88, 80, 94, 90
F24: X/Y | G24: {=Matrix_X/Matrix_Y} -> 1.5882353 | H24: 2.5517241 | I24: 2.2564103 | V24: Q: Construct a matrix with students as rows and subjects as columns. Then find the average marks of each student.
G25: 1.0357143 | H25: 0.72222222 | I25: 0.23595506
X26: Math | Y26: Physics | Z26: Chemistry | AA26: English | AD26: Ave. Marks
B27: ` | W27: Student 1 | X27: 85 | Y27: 78 | Z27: 92 | AA27: 88 | AD27: =AVERAGE(X27:AA27) -> 85.75
W28: Student 2 | X28: 90 | Y28: 82 | Z28: 89 | AA28: 84 | AD28: =AVERAGE(X28:AA28) -> 86.25
W29: Student 3 | X29: 88 | Y29: 80 | Z29: 94 | AA29: 90 | AD29: =AVERAGE(X29:AA29) -> 88

Sheet Simultaneous Equation
B2: Simultaneous Equations
B4: QUES 1 : | C4: A | F4: B | H4: S.no | I4: Steps to Solve Simultaneous Equations | K4: QUES 2 : | L4: A | P4: B
B5: 2x+4y = 40 | C5: 2 | D5: 4 | F5: 40 | H5: 1 | I5: Form coefficient matrix A and constant matrix B | K5: x+2y+3z=14 | L5: 1 | M5: 2 | N5: 3 | P5: 14
B6: 4x+y = 35 | C6: 4 | D6: 1 | F6: 35 | H6: 2 | I6: Find inverse: =MINVERSE(A) | K6: 2x-y+z=3 | L6: 2 | M6: -1 | N6: 1 | P6: 3
H7: 3 | I7: Multiply: =MMULT(A⁻¹, B) | K7: -3x+4y+2z=-1 | L7: -3 | M7: 4 | N7: 2 | P7: -1
H8: 4 | I8: Results give values of x and y
B9: INVERSE | E9: {=MINVERSE(C5:D6)} -> -0.071428571 | F9: 0.28571429 | K9: INVERSE | L9: {=MINVERSE(L5:N7)} -> 1.2 | M9: -1.6 | N9: -1
E10: 0.28571429 | F10: -0.14285714 | L10: 1.4 | M10: -2.2 | N10: -1
L11: -1 | M11: 2 | N11: 1
B12: X | E12: {=MMULT(E9:F10,F5:F6)} -> 7.1428571
B13: Y | E13: 6.4285714 | K13: X | L13: {=MMULT(L9:N11,P5:P7)} -> 13
K14: Y | L14: 14
K15: Z | L15: -9

Sheet Filters
B2: Emp Name | C2: Designation | D2: Basic Salary | E2: HRA | F2: Deductions | G2: No. of projects | H2: Additional pay for project | I2: Work | J2: Final Salary | L2: S.No | M2: QUES : | N2: Ans :
B3: Abhimanyu Pulugurtha | C3: PJM | D3: 26100 | E3: 7417 | F3: 2106 | G3: 1 | H3: =IF(C3="Tester",5000,IF(C3="Manager",20000,IF(C3="PJM",7500,IF(C3="Lead",15000,IF(C3="DB",5000,IF(C3="Developer",10000,IF(C3="Analyst",15000,IF(C3="Associate",7500,IF(C3="CEO",30000))))))))) -> 7500 | I3: Work from home | J3: =D3+E3-F3 -> 31411 | L3: 1 | M3: How many employees work from home? | N3: 32
B4: Girish Kumar | C4: Lead | D4: 220800 | E4: 149217 | F4: 90612 | G4: 4 | H4: =IF(C4="Tester",5000,IF(C4="Manager",20000,IF(C4="PJM",7500,IF(C4="Lead",15000,IF(C4="DB",5000,IF(C4="Developer",10000,IF(C4="Analyst",15000,IF(C4="Associate",7500,IF(C4="CEO",30000))))))))) -> 15000 | I4: Work from home | J4: =D4+E4-F4 -> 279405 | L4: 2 | M4: Find the maximum final salary | N4: 330067
B5: Aditya Kumar | C5: Tester | D5: 150900 | E5: 120695 | F5: 108629 | G5: 1 | H5: =IF(C5="Tester",5000,IF(C5="Manager",20000,IF(C5="PJM",7500,IF(C5="Lead",15000,IF(C5="DB",5000,IF(C5="Developer",10000,IF(C5="Analyst",15000,IF(C5="Associate",7500,IF(C5="CEO",30000))))))))) -> 5000 | I5: Office | J5: =D5+E5-F5 -> 162966 | L5: 3 | M5: How many employees work in office? | N5: 9
B6: Navin Prakash | C6: Manager | D6: 247800 | E6: 165246 | F6: 82979 | G6: 5 | H6: =IF(C6="Tester",5000,IF(C6="Manager",20000,IF(C6="PJM",7500,IF(C6="Lead",15000,IF(C6="DB",5000,IF(C6="Developer",10000,IF(C6="Analyst",15000,IF(C6="Associate",7500,IF(C6="CEO",30000))))))))) -> 20000 | I6: Office | J6: =D6+E6-F6 -> 330067 | L6: 4 | M6: Find the minimum HRA | N6: 532
B7: Swathi Matam | C7: Tester | D7: 50000 | E7: 10000 | F7: 5000 | G7: 2 | H7: =IF(C7="Tester",5000,IF(C7="Manager",20000,IF(C7="PJM",7500,IF(C7="Lead",15000,IF(C7="DB",5000,IF(C7="Developer",10000,IF(C7="Analyst",15000,IF(C7="Associate",7500,IF(C7="CEO",30000))))))))) -> 5000 | I7: Work from home | J7: =D7+E7-F7 -> 55000 | L7: 5 | M7: How many employees have more than 3 projects? | N7: 23
B8: Ankit Kushi | C8: Associate | D8: 36900 | E8: 10977 | F8: 9111 | G8: 3 | H8: =IF(C8="Tester",5000,IF(C8="Manager",20000,IF(C8="PJM",7500,IF(C8="Lead",15000,IF(C8="DB",5000,IF(C8="Developer",10000,IF(C8="Analyst",15000,IF(C8="Associate",7500,IF(C8="CEO",30000))))))))) -> 7500 | I8: Office | J8: =D8+E8-F8 -> 38766 | L8: 6 | M8: Count employees with designation = Manager | N8: 11
B9: Aruna Sabavath | C9: Developer | D9: 192300 | E9: 131443 | F9: 222 | G9: 2 | H9: =IF(C9="Tester",5000,IF(C9="Manager",20000,IF(C9="PJM",7500,IF(C9="Lead",15000,IF(C9="DB",5000,IF(C9="Developer",10000,IF(C9="Analyst",15000,IF(C9="Associate",7500,IF(C9="CEO",30000))))))))) -> 10000 | I9: Office | J9: =D9+E9-F9 -> 323521 | L9: 7 | M9: Find highest salary among Developers | N9: 7
B10: Balaji rajakrishna | C10: Manager | D10: 195900 | E10: 143993 | F10: 46713 | G10: 4 | H10: =IF(C10="Tester",5000,IF(C10="Manager",20000,IF(C10="PJM",7500,IF(C10="Lead",15000,IF(C10="DB",5000,IF(C10="Developer",10000,IF(C10="Analyst",15000,IF(C10="Associate",7500,IF(C10="CEO",30000))))))))) -> 20000 | I10: Office | J10: =D10+E10-F10 -> 293180 | L10: 8 | M10: How many employees have deductions > 5000 | N10: 61
B11: Pranathi Adem | C11: DB | D11: 55200 | E11: 17868 | F11: 15728 | G11: 2 | H11: =IF(C11="Tester",5000,IF(C11="Manager",20000,IF(C11="PJM",7500,IF(C11="Lead",15000,IF(C11="DB",5000,IF(C11="Developer",10000,IF(C11="Analyst",15000,IF(C11="Associate",7500,IF(C11="CEO",30000))))))))) -> 5000 | I11: Work from home | J11: =D11+E11-F11 -> 57340 | L11: 9 | M11: Find employees whose name starts with “A” | N11: 7
B12: Dasarath Daya | C12: Developer | D12: 119400 | E12: 17052 | F12: 9512 | G12: 2 | H12: =IF(C12="Tester",5000,IF(C12="Manager",20000,IF(C12="PJM",7500,IF(C12="Lead",15000,IF(C12="DB",5000,IF(C12="Developer",10000,IF(C12="Analyst",15000,IF(C12="Associate",7500,IF(C12="CEO",30000))))))))) -> 10000 | I12: Office | J12: =D12+E12-F12 -> 126940 | L12: 10 | M12: Find lowest salary among Work from home employees | N12: 31411
B13: Dharani S | C13: Tester | D13: 244200 | E13: 39387 | F13: 7279 | G13: 2 | H13: =IF(C13="Tester",5000,IF(C13="Manager",20000,IF(C13="PJM",7500,IF(C13="Lead",15000,IF(C13="DB",5000,IF(C13="Developer",10000,IF(C13="Analyst",15000,IF(C13="Associate",7500,IF(C13="CEO",30000))))))))) -> 5000 | I13: Office | J13: =D13+E13-F13 -> 276308 | L13: 11 | M13: How many employees: Work from home AND projects ≥ 3 | N13: 19
B14: Maria Malini | C14: Analyst | D14: 236700 | E14: 177157 | F14: 117611 | G14: 2 | H14: =IF(C14="Tester",5000,IF(C14="Manager",20000,IF(C14="PJM",7500,IF(C14="Lead",15000,IF(C14="DB",5000,IF(C14="Developer",10000,IF(C14="Analyst",15000,IF(C14="Associate",7500,IF(C14="CEO",30000))))))))) -> 15000 | I14: Work from home | J14: =D14+E14-F14 -> 296246 | L14: 12 | M14: Find max salary where designation = Analyst | N14: 296246
... B17: Ujwal Chowdavaraj | C17: Lead | D17: 185400 | E17: 100352 | F17: 40072 | G17: 3 | H17: =IF(C17="Tester",5000,IF(C17="Manager",20000,IF(C17="PJM",7500,IF(C17="Lead",15000,IF(C17="DB",5000,IF(C17="Developer",10000,IF(C17="Analyst",15000,IF(C17="Associate",7500,IF(C17="CEO",30000))))))))) -> 15000 | I17: Work from home | J17: =D17+E17-F17 -> 245680 | L17: 15 | M17: How many employees: Additional pay = 5000 | N17: 25
B18: Gundu Kumar | C18: Tester | D18: 126000 | E18: 13803 | F18: 2986 | G18: 4 | H18: =IF(C18="Tester",5000,IF(C18="Manager",20000,IF(C18="PJM",7500,IF(C18="Lead",15000,IF(C18="DB",5000,IF(C18="Developer",10000,IF(C18="Analyst",15000,IF(C18="Associate",7500,IF(C18="CEO",30000))))))))) -> 5000 | I18: Office | J18: =D18+E18-F18 -> 136817
B19: Imam Jani Shaik | C19: DB | D19: 219000 | E19: 37955 | F19: 8471 | G19: 2 | H19: =IF(C19="Tester",5000,IF(C19="Manager",20000,IF(C19="PJM",7500,IF(C19="Lead",15000,IF(C19="DB",5000,IF(C19="Developer",10000,IF(C19="Analyst",15000,IF(C19="Associate",7500,IF(C19="CEO",30000))))))))) -> 5000 | I19: Office | J19: =D19+E19-F19 -> 248484
B20: Vani Golla | C20: DB | D20: 166200 | E20: 119478 | F20: 118048 | G20: 3 | H20: =IF(C20="Tester",5000,IF(C20="Manager",20000,IF(C20="PJM",7500,IF(C20="Lead",15000,IF(C20="DB",5000,IF(C20="Developer",10000,IF(C20="Analyst",15000,IF(C20="Associate",7500,IF(C20="CEO",30000))))))))) -> 5000 | I20: Work from home | J20: =D20+E20-F20 -> 167630
B21: Jayathi Bargal | C21: PJM | D21: 99300 | E21: 90919 | F21: 53126 | G21: 4 | H21: =IF(C21="Tester",5000,IF(C21="Manager",20000,IF(C21="PJM",7500,IF(C21="Lead",15000,IF(C21="DB",5000,IF(C21="Developer",10000,IF(C21="Analyst",15000,IF(C21="Associate",7500,IF(C21="CEO",30000))))))))) -> 7500 | I21: Office | J21: =D21+E21-F21 -> 137093
B22: K Dhanesh | C22: DB | D22: 144600 | E22: 101720 | F22: 84743 | G22: 4 | H22: =IF(C22="Tester",5000,IF(C22="Manager",20000,IF(C22="PJM",7500,IF(C22="Lead",15000,IF(C22="DB",5000,IF(C22="Developer",10000,IF(C22="Analyst",15000,IF(C22="Associate",7500,IF(C22="CEO",30000))))))))) -> 5000 | I22: Office | J22: =D22+E22-F22 -> 161577
B23: Kamal Chalamalasetti | C23: DB | D23: 190500 | E23: 151281 | F23: 62324 | G23: 2 | H23: =IF(C23="Tester",5000,IF(C23="Manager",20000,IF(C23="PJM",7500,IF(C23="Lead",15000,IF(C23="DB",5000,IF(C23="Developer",10000,IF(C23="Analyst",15000,IF(C23="Associate",7500,IF(C23="CEO",30000))))))))) -> 5000 | I23: Office | J23: =D23+E23-F23 -> 279457
B24: Karthik Mulukutla | C24: Developer | D24: 55500 | E24: 10618 | F24: 7429 | G24: 1 | H24: =IF(C24="Tester",5000,IF(C24="Manager",20000,IF(C24="PJM",7500,IF(C24="Lead",15000,IF(C24="DB",5000,IF(C24="Developer",10000,IF(C24="Analyst",15000,IF(C24="Associate",7500,IF(C24="CEO",30000))))))))) -> 10000 | I24: Office | J24: =D24+E24-F24 -> 58689
B25: Kavita Bhatt | C25: Tester | D25: 58500 | E25: 47732 | F25: 23161 | G25: 2 | H25: =IF(C25="Tester",5000,IF(C25="Manager",20000,IF(C25="PJM",7500,IF(C25="Lead",15000,IF(C25="DB",5000,IF(C25="Developer",10000,IF(C25="Analyst",15000,IF(C25="Associate",7500,IF(C25="CEO",30000))))))))) -> 5000 | I25: Work from home | J25: =D25+E25-F25 -> 83071
B26: Rangarajan Subrajani | C26: DB | D26: 163200 | E26: 64822 | F26: 11066 | G26: 3 | H26: =IF(C26="Tester",5000,IF(C26="Manager",20000,IF(C26="PJM",7500,IF(C26="Lead",15000,IF(C26="DB",5000,IF(C26="Developer",10000,IF(C26="Analyst",15000,IF(C26="Associate",7500,IF(C26="CEO",30000))))))))) -> 5000 | I26: Work from home | J26: =D26+E26-F26 -> 216956
B27: Khushi | C27: CEO | D27: 250000 | E27: 50000 | F27: 45000 | G27: 3 | H27: =IF(C27="Tester",5000,IF(C27="Manager",20000,IF(C27="PJM",7500,IF(C27="Lead",15000,IF(C27="DB",5000,IF(C27="Developer",10000,IF(C27="Analyst",15000,IF(C27="Associate",7500,IF(C27="CEO",30000))))))))) -> 30000 | I27: Office | J27: =D27+E27-F27 -> 255000
B28: Kiran Kunaparaju | C28: PJM | D28: 132600 | E28: 74377 | F28: 19474 | G28: 3 | H28: =IF(C28="Tester",5000,IF(C28="Manager",20000,IF(C28="PJM",7500,IF(C28="Lead",15000,IF(C28="DB",5000,IF(C28="Developer",10000,IF(C28="Analyst",15000,IF(C28="Associate",7500,IF(C28="CEO",30000))))))))) -> 7500 | I28: Work from home | J28: =D28+E28-F28 -> 187503
B29: Rajesh Nair | C29: Analyst | D29: 204900 | E29: 76562 | F29: 64409 | G29: 2 | H29: =IF(C29="Tester",5000,IF(C29="Manager",20000,IF(C29="PJM",7500,IF(C29="Lead",15000,IF(C29="DB",5000,IF(C29="Developer",10000,IF(C29="Analyst",15000,IF(C29="Associate",7500,IF(C29="CEO",30000))))))))) -> 15000 | I29: Work from home | J29: =D29+E29-F29 -> 217053
... B80: Gaurav Saurav | C80: Analyst | D80: 57300 | E80: 6558 | F80: 185 | G80: 3 | H80: =IF(C80="Tester",5000,IF(C80="Manager",20000,IF(C80="PJM",7500,IF(C80="Lead",15000,IF(C80="DB",5000,IF(C80="Developer",10000,IF(C80="Analyst",15000,IF(C80="Associate",7500,IF(C80="CEO",30000))))))))) -> 15000 | I80: Office | J80: =D80+E80-F80 -> 63673

Sheet Q1
B2: Q1. Number of Employees by Designation
B3: Count of Final Salary | C3: Column Labels
B4: Row Labels | C4: Office | D4: Work from home | E4: Grand Total
B5: Analyst | C5: 5 | D5: 5 | E5: 10
B6: Associate | C6: 3 | D6: 1 | E6: 4
B7: CEO | C7: 1 | E7: 1
B8: DB | C8: 5 | D8: 5 | E8: 10
B9: Developer | C9: 7 | E9: 7
B10: Lead | C10: 5 | D10: 4 | E10: 9
B11: Manager | C11: 8 | D11: 3 | E11: 11
B12: PJM | C12: 5 | D12: 6 | E12: 11
B13: Tester | C13: 7 | D13: 8 | E13: 15
B14: Grand Total | C14: 46 | D14: 32 | E14: 78

Sheet Q2
B2: Q2. Total Final Salary by Designation
B3: Row Labels | C3: Sum of Final Salary
B4: Analyst | C4: 1559079
B5: Associate | C5: 695843
B6: CEO | C6: 255000
B7: DB | C7: 1580265
B8: Developer | C8: 862980
B9: Lead | C9: 1472394
B10: Manager | C10: 1911804
B11: PJM | C11: 1178051
B12: Tester | C12: 2269464
B13: Grand Total | C13: 11784880

Sheet Q3
B2: Q3. Average Basic Salary by Work Type
B3: Row Labels | C3: Average of Basic Salary
B4: Office | C4: 121910.87
B5: Work from home | C5: 122743.75
B6: Grand Total | C6: 122252.56

Sheet Q4
B2: Q4. Total Additional Pay by No. of Projects
B3: Row Labels | C3: Sum of Additional pay for project
B4: 1 | C4: 57500
B5: 2 | C5: 210000
B6: 3 | C6: 247500
B7: 4 | C7: 207500
B8: 5 | C8: 120000
B9: Grand Total | C9: 842500

Sheet CATEGORIZATION
B2: Categorization using Vlookup / JOINING Tables
B3: Invoice ID | C3: Date | D3: Branch | E3: City | F3: Customer type | G3: Gender | H3: Product | I3: Category | J3: Cost Price | K3: Selling Price | L3: Quantity | M3: Payment | N3: Rating | O3: Profit | R3: PRODUCT TABLE
B4: 750-67-8428 | C4: 43586 | D4: A | E4: Chennai | F4: Member | G4: Female | H4: Toner | I4: =VLOOKUP(H4,$R$5:$S$32,2,FALSE) -> Health and beauty | J4: 74.69 | K4: 78.4245 | L4: 7 | M4: Ewallet | N4: 9.1 | O4: =(CATEGORIZATION!$K4-CATEGORIZATION!$J4) -> 3.7345 | R4: Product | S4: Category
B5: 226-31-3081 | C5: 43680 | D5: C | E5: Mumbai | F5: Normal | G5: Female | H5: USB | I5: =VLOOKUP(H5,$R$5:$S$32,2,FALSE) -> Electronic accessories | J5: 15.28 | K5: 16.044 | L5: 5 | M5: Cash | N5: 9.6 | O5: =(CATEGORIZATION!$K5-CATEGORIZATION!$J5) -> 0.764 | R5: Basket Ball | S5: Sports
B6: 123-19-1176 | C6: 43492 | D6: A | E6: Chennai | F6: Member | G6: Female | H6: Serum | I6: =VLOOKUP(H6,$R$5:$S$32,2,FALSE) -> Health and beauty | J6: 58.22 | K6: 61.131 | L6: 8 | M6: Ewallet | N6: 8.4 | O6: =(CATEGORIZATION!$K6-CATEGORIZATION!$J6) -> 2.911 | R6: Biscuit | S6: Food and beverages
B7: 373-73-7910 | C7: 43679 | D7: A | E7: Chennai | F7: Normal | G7: Female | H7: Basket Ball | I7: =VLOOKUP(H7,$R$5:$S$32,2,FALSE) -> Sports | J7: 86.31 | K7: 90.6255 | L7: 7 | M7: Ewallet | N7: 5.3 | O7: =(CATEGORIZATION!$K7-CATEGORIZATION!$J7) -> 4.3155 | R7: Body Lotion | S7: Health and beauty
B8: 699-14-3026 | C8: 43549 | D8: C | E8: Mumbai | F8: Normal | G8: Female | H8: Charger | J8: 85.39 | K8: 89.6595 | L8: 7 | M8: Ewallet | N8: 4.1 | O8: =(CATEGORIZATION!$K8-CATEGORIZATION!$J8) -> 4.2695 | R8: Bread | S8: Food and beverages
B9: 355-53-5943 | C9: 43521 | D9: A | E9: Chennai | F9: Member | G9: Female | H9: Earplugs | I9: =VLOOKUP(H9,$R$5:$S$32,2,FALSE) -> Electronic accessories | J9: 68.84 | K9: 72.282 | L9: 6 | M9: Ewallet | N9: 5.8 | O9: =(CATEGORIZATION!$K9-CATEGORIZATION!$J9) -> 3.442 | R9: Charger | S9: Electronic accessories
B10: 665-32-9167 | C10: 43739 | D10: A | E10: Chennai | F10: Member | G10: Female | H10: Soap | I10: =VLOOKUP(H10,$R$5:$S$32,2,FALSE) -> Health and beauty | J10: 36.26 | K10: 38.073 | L10: 2 | M10: Credit card | N10: 7.2 | O10: =(CATEGORIZATION!$K10-CATEGORIZATION!$J10) -> 1.813 | R10: Chocolates | S10: Food and beverages
B11: 692-92-5582 | C11: 43516 | D11: B | E11: Delhi | F11: Member | G11: Female | H11: Soda | I11: =VLOOKUP(H11,$R$5:$S$32,2,FALSE) -> Food and beverages | J11: 54.84 | K11: 57.582 | L11: 3 | M11: Credit card | N11: 5.9 | O11: =(CATEGORIZATION!$K11-CATEGORIZATION!$J11) -> 2.742 | R11: Deodrant | S11: Health and beauty
B12: 529-56-3974 | C12: 43711 | D12: B | E12: Delhi | F12: Member | G12: Female | H12: Hard Disk | I12: =VLOOKUP(H12,$R$5:$S$32,2,FALSE) -> Electronic accessories | J12: 25.51 | K12: 26.7855 | L12: 4 | M12: Cash | N12: 6.8 | O12: =(CATEGORIZATION!$K12-CATEGORIZATION!$J12) -> 1.2755 | R12: Earplugs | S12: Electronic accessories
B13: 365-64-0515 | C13: 43801 | D13: A | E13: Chennai | F13: Normal | G13: Female | H13: Hard Disk | I13: =VLOOKUP(H13,$R$5:$S$32,2,FALSE) -> Electronic accessories | J13: 46.95 | K13: 49.2975 | L13: 5 | M13: Ewallet | N13: 7.1 | O13: =(CATEGORIZATION!$K13-CATEGORIZATION!$J13) -> 2.3475 | R13: Energy Drink | S13: Food and beverages
B14: 252-56-2699 | C14: 43648 | D14: A | E14: Chennai | F14: Normal | G14: Female | H14: Bread | I14: =VLOOKUP(H14,$R$5:$S$32,2,FALSE) -> Food and beverages | J14: 43.19 | K14: 45.3495 | L14: 10 | M14: Ewallet | N14: 8.2 | O14: =(CATEGORIZATION!$K14-CATEGORIZATION!$J14) -> 2.1595 | R14: Face Wash | S14: Health and beauty
B15: 829-34-3910 | C15: 43553 | D15: A | E15: Chennai | F15: Normal | G15: Female | H15: Body Lotion | I15: =VLOOKUP(H15,$R$5:$S$32,2,FALSE) -> Health and beauty | J15: 71.38 | K15: 74.949 | L15: 10 | M15: Cash | N15: 5.7 | O15: =(CATEGORIZATION!$K15-CATEGORIZATION!$J15) -> 3.569 | R15: Football | S15: Sports
B16: 299-46-1805 | C16: 43480 | D16: B | E16: Delhi | F16: Member | G16: Female | H16: Football | I16: =VLOOKUP(H16,$R$5:$S$32,2,FALSE) -> Sports | J16: 93.72 | K16: 98.406 | L16: 6 | M16: Cash | N16: 4.5 | O16: =(CATEGORIZATION!$K16-CATEGORIZATION!$J16) -> 4.686 | R16: Gloves | S16: Sports
B17: 656-95-9349 | C17: 43772 | D17: A | E17: Chennai | F17: Member | G17: Female | H17: Shampoo | I17: =VLOOKUP(H17,$R$5:$S$32,2,FALSE) -> Health and beauty | J17: 68.93 | K17: 72.3765 | L17: 7 | M17: Credit card | N17: 4.6 | O17: =(CATEGORIZATION!$K17-CATEGORIZATION!$J17) -> 3.4465 | R17: Hard Disk | S17: Electronic accessories
B18: 765-26-6951 | C18: 43466 | D18: A | E18: Chennai | F18: Normal | G18: Female | H18: Gloves | I18: =VLOOKUP(H18,$R$5:$S$32,2,FALSE) -> Sports | J18: 72.61 | K18: 76.2405 | L18: 6 | M18: Credit card | N18: 6.9 | O18: =(CATEGORIZATION!$K18-CATEGORIZATION!$J18) -> 3.6305 | R18: Imported Tiffans | S18: Food and beverages
B19: 329-62-1586 | C19: 43486 | D19: A | E19: Chennai | F19: Normal | G19: Female | H19: Imported Tiffans | I19: =VLOOKUP(H19,$R$5:$S$32,2,FALSE) -> Food and beverages | J19: 54.67 | K19: 57.4035 | L19: 3 | M19: Credit card | N19: 8.6 | O19: =(CATEGORIZATION!$K19-CATEGORIZATION!$J19) -> 2.7335 | R19: Power bank | S19: Electronic accessories
B20: 300-71-4605 | C20: 43521 | D20: C | E20: Mumbai | F20: Member | G20: Female | H20: Earplugs | I20: =VLOOKUP(H20,$R$5:$S$32,2,FALSE) -> Electronic accessories | J20: 86.04 | K20: 90.342 | L20: 5 | M20: Ewallet | N20: 4.8 | O20: =(CATEGORIZATION!$K20-CATEGORIZATION!$J20) -> 4.302 | R20: Pump | S20: Sports
... B32: 272-65-1806 | C32: 43480 | D32: A | E32: Chennai | F32: Normal | G32: Female | H32: Hard Disk | I32: =VLOOKUP(H32,$R$5:$S$32,2,FALSE) -> Electronic accessories | J32: 60.88 | K32: 63.924 | L32: 9 | M32: Ewallet | N32: 4.7 | O32: =(CATEGORIZATION!$K32-CATEGORIZATION!$J32) -> 3.044 | R32: Wristband | S32: Sports
B33: 333-73-7901 | C33: 43547 | D33: C | E33: Mumbai | F33: Normal | G33: Female | H33: Deodrant | I33: =VLOOKUP(H33,$R$5:$S$32,2,FALSE) -> Health and beauty | J33: 54.92 | K33: 57.666 | L33: 8 | M33: Ewallet | N33: 7.6 | O33: =(CATEGORIZATION!$K33-CATEGORIZATION!$J33) -> 2.746
B34: 354-25-5821 | C34: 43679 | D34: B | E34: Delhi | F34: Member | G34: Female | H34: Football | I34: =VLOOKUP(H34,$R$5:$S$32,2,FALSE) -> Sports | J34: 69.12 | K34: 72.576 | L34: 6 | M34: Cash | N34: 5.6 | O34: =(CATEGORIZATION!$K34-CATEGORIZATION!$J34) -> 3.456
B35: 228-96-1411 | C35: 43558 | D35: C | E35: Mumbai | F35: Member | G35: Female | H35: Energy Drink | I35: =VLOOKUP(H35,$R$5:$S$32,2,FALSE) -> Food and beverages | J35: 98.7 | K35: 103.635 | L35: 8 | M35: Cash | N35: 7.6 | O35: =(CATEGORIZATION!$K35-CATEGORIZATION!$J35) -> 4.935
B36: 617-15-4209 | C36: 43540 | D36: C | E36: Mumbai | F36: Member | G36: Female | H36: Body Lotion | I36: =VLOOKUP(H36,$R$5:$S$32,2,FALSE) -> Health and beauty | J36: 15.37 | K36: 16.1385 | L36: 2 | M36: Cash | N36: 7.2 | O36: =(CATEGORIZATION!$K36-CATEGORIZATION!$J36) -> 0.7685
B37: 132-32-9879 | C37: 43711 | D37: B | E37: Delhi | F37: Member | G37: Female | H37: Hard Disk | I37: =VLOOKUP(H37,$R$5:$S$32,2,FALSE) -> Electronic accessories | J37: 93.96 | K37: 98.658 | L37: 4 | M37: Cash | N37: 9.5 | O37: =(CATEGORIZATION!$K37-CATEGORIZATION!$J37) -> 4.698
B38: 370-41-7321 | C38: 43523 | D38: B | E38: Delhi | F38: Member | G38: Female | H38: Deodrant | I38: =VLOOKUP(H38,$R$5:$S$32,2,FALSE) -> Health and beauty | J38: 56.69 | K38: 59.5245 | L38: 9 | M38: Credit card | N38: 8.4 | O38: =(CATEGORIZATION!$K38-CATEGORIZATION!$J38) -> 2.8345
B39: 727-46-3608 | C39: 43618 | D39: B | E39: Delhi | F39: Member | G39: Female | H39: Biscuit | I39: =VLOOKUP(H39,$R$5:$S$32,2,FALSE) -> Food and beverages | J39: 20.01 | K39: 21.0105 | L39: 9 | M39: Ewallet | N39: 4.1 | O39: =(CATEGORIZATION!$K39-CATEGORIZATION!$J39) -> 1.0005
B40: 669-54-1719 | C40: 43740 | D40: B | E40: Delhi | F40: Member | G40: Female | H40: Hard Disk | I40: =VLOOKUP(H40,$R$5:$S$32,2,FALSE) -> Electronic accessories | J40: 18.93 | K40: 19.8765 | L40: 6 | M40: Credit card | N40: 8.1 | O40: =(CATEGORIZATION!$K40-CATEGORIZATION!$J40) -> 0.9465
B41: 326-78-5178 | C41: 43526 | D41: C | E41: Mumbai | F41: Member | G41: Female | H41: Biscuit | I41: =VLOOKUP(H41,$R$5:$S$32,2,FALSE) -> Food and beverages | J41: 91.4 | K41: 95.97 | L41: 7 | M41: Cash | N41: 9.5 | O41: =(CATEGORIZATION!$K41-CATEGORIZATION!$J41) -> 4.57
B42: 162-48-8011 | C42: 43740 | D42: A | E42: Chennai | F42: Member | G42: Female | H42: Biscuit | I42: =VLOOKUP(H42,$R$5:$S$32,2,FALSE) -> Food and beverages | J42: 44.59 | K42: 46.8195 | L42: 5 | M42: Cash | N42: 8.5 | O42: =(CATEGORIZATION!$K42-CATEGORIZATION!$J42) -> 2.2295
B43: 399-46-5918 | C43: 43524 | D43: C | E43: Mumbai | F43: Normal | G43: Female | H43: USB | I43: =VLOOKUP(H43,$R$5:$S$32,2,FALSE) -> Electronic accessories | J43: 85.98 | K43: 90.279 | L43: 8 | M43: Cash | N43: 8.2 | O43: =(CATEGORIZATION!$K43-CATEGORIZATION!$J43) -> 4.299
B44: 635-40-6220 | C44: 43648 | D44: A | E44: Chennai | F44: Normal | G44: Female | H44: Deodrant | I44: =VLOOKUP(H44,$R$5:$S$32,2,FALSE) -> Health and beauty | J44: 89.6 | K44: 94.08 | L44: 8 | M44: Ewallet | N44: 6.6 | O44: =(CATEGORIZATION!$K44-CATEGORIZATION!$J44) -> 4.48
... B665: 727-02-1313 | C665: 43710 | D665: A | E665: Chennai | F665: Member | G665: Male | H665: Biscuit | I665: =VLOOKUP(H665,$R$5:$S$32,2,FALSE) -> Food and beverages | J665: 31.84 | K665: 33.432 | L665: 1 | M665: Cash | N665: 7.7 | O665: =(CATEGORIZATION!$K665-CATEGORIZATION!$J665) -> 1.592

Sheet Pivot Analyze
B2: Invoice ID | C2: Date | D2: Branch | E2: City | F2: Customer type | G2: Gender | H2: Product | I2: Category | J2: Cost Price | K2: Selling Price | L2: Quantity | M2: Payment | N2: Rating | O2: Profit
B3: 750-67-8428 | C3: 43586 | D3: A | E3: Chennai | F3: Member | G3: Female | H3: Toner | I3: Health and beauty | J3: 74.69 | K3: 78.4245 | L3: 7 | M3: Ewallet | N3: 9.1 | O3: 3.7345
B4: 226-31-3081 | C4: 43587 | D4: C | E4: Mumbai | F4: Normal | G4: Female | H4: USB | I4: Electronic accessories | J4: 15.28 | K4: 16.044 | L4: 5 | M4: Cash | N4: 9.6 | O4: 0.764
B5: 123-19-1176 | C5: 43588 | D5: A | E5: Chennai | F5: Member | G5: Female | H5: Serum | I5: Health and beauty | J5: 58.22 | K5: 61.131 | L5: 8 | M5: Ewallet | N5: 8.4 | O5: 2.911
B6: 373-73-7910 | C6: 43589 | D6: A | E6: Chennai | F6: Normal | G6: Female | H6: Basket Ball | I6: Sports | J6: 86.31 | K6: 90.6255 | L6: 7 | M6: Ewallet | N6: 5.3 | O6: 4.3155
B7: 699-14-3026 | C7: 43590 | D7: C | E7: Mumbai | F7: Normal | G7: Female | H7: Charger | J7: 85.39 | K7: 89.6595 | L7: 7 | M7: Ewallet | N7: 4.1 | O7: 4.2695
B8: 355-53-5943 | C8: 43591 | D8: A | E8: Chennai | F8: Member | G8: Female | H8: Earplugs | I8: Electronic accessories | J8: 68.84 | K8: 72.282 | L8: 6 | M8: Ewallet | N8: 5.8 | O8: 3.442
B9: 665-32-9167 | C9: 43592 | D9: A | E9: Chennai | F9: Member | G9: Female | H9: Soap | I9: Health and beauty | J9: 36.26 | K9: 38.073 | L9: 2 | M9: Credit card | N9: 7.2 | O9: 1.813
B10: 692-92-5582 | C10: 43593 | D10: B | E10: Delhi | F10: Member | G10: Female | H10: Soda | I10: Food and beverages | J10: 54.84 | K10: 57.582 | L10: 3 | M10: Credit card | N10: 5.9 | O10: 2.742
B11: 529-56-3974 | C11: 43594 | D11: B | E11: Delhi | F11: Member | G11: Female | H11: Hard Disk | I11: Electronic accessories | J11: 25.51 | K11: 26.7855 | L11: 4 | M11: Cash | N11: 6.8 | O11: 1.2755
B12: 365-64-0515 | C12: 43595 | D12: A | E12: Chennai | F12: Normal | G12: Female | H12: Hard Disk | I12: Electronic accessories | J12: 46.95 | K12: 49.2975 | L12: 5 | M12: Ewallet | N12: 7.1 | O12: 2.3475
B13: 252-56-2699 | C13: 43596 | D13: A | E13: Chennai | F13: Normal | G13: Female | H13: Bread | I13: Food and beverages | J13: 43.19 | K13: 45.3495 | L13: 10 | M13: Ewallet | N13: 8.2 | O13: 2.1595
B14: 829-34-3910 | C14: 43597 | D14: A | E14: Chennai | F14: Normal | G14: Female | H14: Body Lotion | I14: Health and beauty | J14: 71.38 | K14: 74.949 | L14: 10 | M14: Cash | N14: 5.7 | O14: 3.569
B15: 299-46-1805 | C15: 43598 | D15: B | E15: Delhi | F15: Member | G15: Female | H15: Football | I15: Sports | J15: 93.72 | K15: 98.406 | L15: 6 | M15: Cash | N15: 4.5 | O15: 4.686
B16: 656-95-9349 | C16: 43599 | D16: A | E16: Chennai | F16: Member | G16: Female | H16: Shampoo | I16: Health and beauty | J16: 68.93 | K16: 72.3765 | L16: 7 | M16: Credit card | N16: 4.6 | O16: 3.4465
B17: 765-26-6951 | C17: 43600 | D17: A | E17: Chennai | F17: Normal | G17: Female | H17: Gloves | I17: Sports | J17: 72.61 | K17: 76.2405 | L17: 6 | M17: Credit card | N17: 6.9 | O17: 3.6305
B18: 329-62-1586 | C18: 43601 | D18: A | E18: Chennai | F18: Normal | G18: Female | H18: Imported Tiffans | I18: Food and beverages | J18: 54.67 | K18: 57.4035 | L18: 3 | M18: Credit card | N18: 8.6 | O18: 2.7335
B19: 300-71-4605 | C19: 43602 | D19: C | E19: Mumbai | F19: Member | G19: Female | H19: Earplugs | I19: Electronic accessories | J19: 86.04 | K19: 90.342 | L19: 5 | M19: Ewallet | N19: 4.8 | O19: 4.302
... B664: 727-02-1313 | C664: 44247 | D664: A | E664: Chennai | F664: Member | G664: Male | H664: Biscuit | I664: Food and beverages | J664: 31.84 | K664: 33.432 | L664: 1 | M664: Cash | N664: 7.7 | O664: 1.592

Sheet A
B2: What product is bought in Chennai with rating 4.4 by male non member ?
B3: Row Labels | C3: Count of Product
B4: Chennai | C4: 2
B5: Grand Total | C5: 2

Sheet B
B2: Which category has the highest rating given by normal customer in Delhi in Oct 2019
B3: Row Labels | C3: Max of Rating
B4: Food and beverages | C4: 4.2
B5: Health and beauty | C5: 8
B6: Sports | C6: 7.9
B7: Grand Total | C7: 8

Sheet C
B2: What is the profit for a product sold to male member in MUMBAI with rating above 8
B3: Row Labels | C3: Sum of Profit
B4: Charger | C4: 1.853
B5: Chocolates | C5: 2.255
B6: Deodrant | C6: 7.489
B7: Energy Drink | C7: 4.713
B8: Face Wash | C8: 6.5435
B9: Football | C9: 2.1425
B10: Pump | C10: 8.193
B11: Skipping Rope | C11: 2.9195
B12: Tera Band | C12: 0.735
B13: Toner | C13: 4.525
B14: USB | C14: 4.0985
B15: Water | C15: 2.9795
B16: Grand Total | C16: 48.4465

Sheet CONDITIONAL FORMATTING
B2: CONDITIONAL FORMATTING
B3: >7 (GREEN) | C3: <4 (RED) | D3: Between 5-8 (GREY) | E3: "=9" (BLUE) | G3: Text that contain AR | I3: DATA BARS | J3: COLOR SCALES | K3: ICONS | M3: For Blank Spaces
B4: Quantity | C4: Quantity2 | D4: Quantity3 | E4: Quantity4 | G4: Product ID | I4: 123 | J4: 123 | K4: 123 | M4: 12
B5: 7 | C5: 7 | D5: 7 | E5: 7 | G5: AR123 | I5: 542 | J5: 542 | K5: 542
B6: 5 | C6: 5 | D6: 5 | E6: 5 | G6: TR123 | I6: 865 | J6: 865 | K6: 865 | M6: 34
B7: 8 | C7: 8 | D7: 8 | E7: 8 | G7: AR345 | I7: 884 | J7: 884 | K7: 884
B8: 7 | C8: 7 | D8: 7 | E8: 7 | G8: ART56 | I8: 764 | J8: 764 | K8: 764
B9: 7 | C9: 7 | D9: 7 | E9: 7 | G9: BR456 | I9: 670 | J9: 670 | K9: 670
B10: 6 | C10: 6 | D10: 6 | E10: 6 | I10: 600 | J10: 600 | K10: 600 | M10: 56
B11: 2 | C11: 2 | D11: 2 | E11: 2 | I11: 823 | J11: 823 | K11: 823
B12: 3 | C12: 3 | D12: 3 | E12: 3 | I12: 205 | J12: 205 | K12: 205 | M12: 77
B13: 4 | C13: 4 | D13: 4 | E13: 4 | I13: 103 | J13: 103 | K13: 103
B14: 5 | C14: 5 | D14: 5 | E14: 5 | I14: 759 | J14: 759 | K14: 759
B15: 10 | C15: 10 | D15: 10 | E15: 10 | I15: 239 | J15: 239 | K15: 239
B16: 10 | C16: 10 | D16: 10 | E16: 10 | I16: 141 | J16: 141 | K16: 141
B17: 6 | C17: 6 | D17: 6 | E17: 6
B18: 7 | C18: 7 | D18: 7 | E18: 7
B19: 6 | C19: 6 | D19: 6 | E19: 6
B20: 3 | C20: 3 | D20: 3 | E20: 3
B21: 5 | C21: 5 | D21: 5 | E21: 5
B22: 3 | C22: 3 | D22: 3 | E22: 3
B23: 5 | C23: 5 | D23: 5 | E23: 5
B24: 3 | C24: 3 | D24: 3 | E24: 3
B25: 5 | C25: 5 | D25: 5 | E25: 5
B26: 9 | C26: 9 | D26: 9 | E26: 9
B27: 9 | C27: 9 | D27: 9 | E27: 9
B28: 8 | C28: 8 | D28: 8 | E28: 8
... B666: 1 | C666: 1 | D666: 1 | E666: 1

Sheet Sheet1
